stroll.py
stroll-1.1.0.dist-info/LICENSE
stroll-1.1.0.dist-info/METADATA
stroll-1.1.0.dist-info/WHEEL
stroll-1.1.0.dist-info/top_level.txt
stroll-1.1.0.dist-info/RECORD
