Metadata-Version: 1.1
Name: stroll
Version: 1.1.0
Summary: Better os.walk
Home-page: https://github.com/rec/stroll
Author: Tom Ritchford
Author-email: tom@swirly.com
License: MIT
Keywords: os.walk
Platform: UNKNOWN
Classifier: Development Status :: 5 - Production/Stable
Classifier: Programming Language :: Python :: 2.7
Classifier: Programming Language :: Python :: 3.6
Classifier: Programming Language :: Python :: 3.7
Classifier: Programming Language :: Python :: 3.8
Classifier: Programming Language :: Python :: 3.9
Classifier: Intended Audience :: Developers
Classifier: License :: OSI Approved :: MIT License
Classifier: Topic :: Software Development :: Libraries
Classifier: Topic :: Utilities
